expman/__init__.py
expman/analysis.py
expman/cli.py
expman/experiment.py
expman/io.py
expman/static/assets/main-C5P3c9x9.js
expman/static/assets/main-CTWrfuVq.js
expman/static/assets/main-ChBzYkoW.js
expman/static/assets/main-ClINSCAR.css
expman/static/assets/main-D6BeI0_N.css
expman/static/assets/main-DAHhC57S.css
expman/static/assets/main-Pyb7PkEX.js
expman/static/assets/plotly-D2eyJzy6.js
expman/static/index.html
expman/web.py
ra_expman-0.2.7.dist-info/licenses/LICENSE
ra_expman-0.2.7.dist-info/WHEEL
ra_expman-0.2.7.dist-info/entry_points.txt
ra_expman-0.2.7.dist-info/METADATA
ra_expman-0.2.7.dist-info/RECORD
