Metadata-Version: 2.4
Name: ra-expman
Version: 0.2.7
Summary: Manage your experiments exactly as you like
Author: Lokesh Mohanty
Author-email: Lokesh Mohanty <lokesh1197@gmail.com>
License-Expression: MIT
License-File: LICENSE
Classifier: Intended Audience :: Developers
Classifier: Intended Audience :: Science/Research
Classifier: License :: OSI Approved :: MIT License
Classifier: Operating System :: OS Independent
Classifier: Programming Language :: Python :: 3
Classifier: Topic :: Scientific/Engineering
Classifier: Topic :: Scientific/Engineering :: Artificial Intelligence
Classifier: Topic :: Software Development :: Libraries :: Python Modules
Classifier: Topic :: System :: Logging
Classifier: Framework :: FastAPI
Requires-Dist: loguru>=0.7.0
Requires-Dist: polars>=1.0.0
Requires-Dist: pyyaml>=6.0
Requires-Dist: matplotlib>=3.7.0
Requires-Dist: fastapi>=0.110.0
Requires-Dist: uvicorn>=0.27.0
Requires-Dist: pyarrow>=14.0.0
Requires-Dist: torch>=2.0.0 ; extra == 'torch'
Requires-Dist: torchview>=0.2.7 ; extra == 'torch'
Requires-Dist: graphviz>=0.21 ; extra == 'torch'
Requires-Python: >=3.12
Project-URL: Homepage, https://github.com/lokeshmohanty/expman
Project-URL: Issues, https://github.com/lokeshmohanty/expman/issues
Project-URL: Documentation, https://github.com/lokeshmohanty/expman/README.md
Provides-Extra: torch
